<?xml version="1.0" encoding="UTF-8" standalone="yes"?>
<Declaration xmlns:urn="urn:WCOLibraryE7TAXUDEUCDM52public">
  <functionalReference>
    <Identifier.Content>string</Identifier.Content>
  </functionalReference>
  <procedureCategory>
    <Identifier.Content>string</Identifier.Content>
  </procedureCategory>
  <FunctionCode>
    <Code.Content>token</Code.Content>
  </FunctionCode>
  <ExitOffice>
    <identification>
      <Identifier.Content>string</Identifier.Content>
    </identification>
  </ExitOffice>
  <Agent>
    <identification_2>
      <Identifier.Content>string</Identifier.Content>
    </identification_2>
    <Contact>
      <!--Optional:-->
      <sequence>
        <Numeric.Content>1000.00</Numeric.Content>
      </sequence>
      <!--Optional:-->
      <name>
        <Text.Content>string</Text.Content>
      </name>
      <!--Optional:-->
      <Communication>
        <!--Optional:-->
        <sequence>
          <Numeric.Content>1000.00</Numeric.Content>
        </sequence>
        <!--Optional:-->
        <identification_2>
          <Identifier.Content>string</Identifier.Content>
        </identification_2>
        <!--Optional:-->
        <type_8>
          <Code.Content>token</Code.Content>
        </type_8>
      </Communication>
    </Contact>
    <!--Optional:-->
    <sequence>
      <Numeric.Content>1000.00</Numeric.Content>
    </sequence>
    <!--Optional:-->
    <function_3>
      <Code.Content>token</Code.Content>
    </function_3>
  </Agent>
  <Declarant>
    <identification_2>
      <Identifier.Content>string</Identifier.Content>
    </identification_2>
    <Contact>
      <sequence>
        <Numeric.Content>1000.00</Numeric.Content>
      </sequence>
      <!--Optional:-->
      <name>
        <Text.Content>string</Text.Content>
      </name>
      <Communication>
        <sequence>
          <Numeric.Content>1000.00</Numeric.Content>
        </sequence>
        <identification_2>
          <Identifier.Content>string</Identifier.Content>
        </identification_2>
        <type_8>
          <Code.Content>token</Code.Content>
        </type_8>
      </Communication>
    </Contact>
  </Declarant>
  <Submitter>
    <!--Optional:-->
    <name>
      <Text.Content>string</Text.Content>
    </name>
    <identification_2>
      <Identifier.Content>string</Identifier.Content>
    </identification_2>
    <!--Optional:-->
    <sequence>
      <Numeric.Content>1000.00</Numeric.Content>
    </sequence>
  </Submitter>
  <Consignment>
    <sequence>
      <Numeric.Content>1000.00</Numeric.Content>
    </sequence>
    <container>
      <Code.Content>token</Code.Content>
    </container>
    <totalGrossMass>
      <Measure.Content>1000.00</Measure.Content>
    </totalGrossMass>
    <AdditionalInformation>
      <sequence>
        <Numeric.Content>1000.00</Numeric.Content>
      </sequence>
      <!--Optional:-->
      <statement>
        <Code.Content>token</Code.Content>
      </statement>
      <!--Optional:-->
      <statementDescription>
        <Text.Content>string</Text.Content>
      </statementDescription>
    </AdditionalInformation>
    <AEOMutualRecognitionParty>
      <identification_2>
        <Identifier.Content>string</Identifier.Content>
      </identification_2>
      <!--Optional:-->
      <role>
        <Code.Content>token</Code.Content>
      </role>
      <!--Optional:-->
      <sequence>
        <Numeric.Content>1000.00</Numeric.Content>
      </sequence>
    </AEOMutualRecognitionParty>
    <Carrier>
      <identification_2>
        <Identifier.Content>string</Identifier.Content>
      </identification_2>
      <Contact>
        <sequence>
          <Numeric.Content>1000.00</Numeric.Content>
        </sequence>
        <name>
          <Text.Content>string</Text.Content>
        </name>
        <Communication>
          <sequence>
            <Numeric.Content>1000.00</Numeric.Content>
          </sequence>
          <identification_2>
            <Identifier.Content>string</Identifier.Content>
          </identification_2>
          <type_8>
            <Code.Content>token</Code.Content>
          </type_8>
        </Communication>
      </Contact>
      <!--Optional:-->
      <sequence>
        <Numeric.Content>1000.00</Numeric.Content>
      </sequence>
    </Carrier>
    <Consignee>
      <!--Optional:-->
      <name>
        <Text.Content>string</Text.Content>
      </name>
      <identification_2>
        <Identifier.Content>string</Identifier.Content>
      </identification_2>
      <Address>
        <!--Optional:-->
        <sequence>
          <Numeric.Content>1000.00</Numeric.Content>
        </sequence>
        <!--Optional:-->
        <cityName>
          <Text.Content>string</Text.Content>
        </cityName>
        <!--Optional:-->
        <country>
          <Code.Content>token</Code.Content>
        </country>
        <!--Optional:-->
        <line>
          <Text.Content>string</Text.Content>
        </line>
        <!--Optional:-->
        <postcode>
          <Identifier.Content>string</Identifier.Content>
        </postcode>
      </Address>
      <!--Optional:-->
      <sequence>
        <Numeric.Content>1000.00</Numeric.Content>
      </sequence>
    </Consignee>
    <ConsignmentItem>
      <sequence>
        <Numeric.Content>1000.00</Numeric.Content>
      </sequence>
      <Packaging>
        <sequence>
          <Numeric.Content>1000.00</Numeric.Content>
        </sequence>
        <marksNumbers>
          <Identifier.Content>string</Identifier.Content>
        </marksNumbers>
        <quantity>
          <Quantity.Content>1000.00</Quantity.Content>
        </quantity>
        <type_6>
          <Code.Content>token</Code.Content>
        </type_6>
      </Packaging>
      <AdditionalInformation>
        <sequence>
          <Numeric.Content>1000.00</Numeric.Content>
        </sequence>
        <!--Optional:-->
        <statement>
          <Code.Content>token</Code.Content>
        </statement>
        <!--Optional:-->
        <statementDescription>
          <Text.Content>string</Text.Content>
        </statementDescription>
      </AdditionalInformation>
      <AEOMutualRecognitionParty>
        <identification_2>
          <Identifier.Content>string</Identifier.Content>
        </identification_2>
        <!--Optional:-->
        <role>
          <Code.Content>token</Code.Content>
        </role>
        <!--Optional:-->
        <sequence>
          <Numeric.Content>1000.00</Numeric.Content>
        </sequence>
      </AEOMutualRecognitionParty>
      <Commodity>
        <sequence>
          <Numeric.Content>1000.00</Numeric.Content>
        </sequence>
        <description>
          <Text.Content>string</Text.Content>
          <!--Optional:-->
          <Language.Identifier>string</Language.Identifier>
        </description>
        <Classification>
          <!--Optional:-->
          <sequence>
            <Numeric.Content>1000.00</Numeric.Content>
          </sequence>
          <identification_2>
            <Identifier.Content>string</Identifier.Content>
          </identification_2>
          <identificationType_3>
            <Code.Content>token</Code.Content>
          </identificationType_3>
        </Classification>
        <DangerousGoods>
          <sequence>
            <Numeric.Content>1000.00</Numeric.Content>
          </sequence>
          <UNDG>
            <Identifier.Content>string</Identifier.Content>
          </UNDG>
        </DangerousGoods>
      </Commodity>
      <Consignee>
        <name>
          <Text.Content>string</Text.Content>
        </name>
        <identification_2>
          <Identifier.Content>string</Identifier.Content>
        </identification_2>
        <Address>
          <sequence>
            <Numeric.Content>1000.00</Numeric.Content>
          </sequence>
          <cityName>
            <Text.Content>string</Text.Content>
          </cityName>
          <country>
            <Code.Content>token</Code.Content>
          </country>
          <line>
            <Text.Content>string</Text.Content>
          </line>
          <!--Optional:-->
          <postcode>
            <Identifier.Content>string</Identifier.Content>
          </postcode>
        </Address>
        <sequence>
          <Numeric.Content>1000.00</Numeric.Content>
        </sequence>
      </Consignee>
      <Consignor>
        <name>
          <Text.Content>string</Text.Content>
        </name>
        <identification_2>
          <Identifier.Content>string</Identifier.Content>
        </identification_2>
        <Address>
          <sequence>
            <Numeric.Content>1000.00</Numeric.Content>
          </sequence>
          <cityName>
            <Text.Content>string</Text.Content>
          </cityName>
          <country>
            <Code.Content>token</Code.Content>
          </country>
          <line>
            <Text.Content>string</Text.Content>
          </line>
          <postcode>
            <Identifier.Content>string</Identifier.Content>
          </postcode>
        </Address>
        <sequence>
          <Numeric.Content>1000.00</Numeric.Content>
        </sequence>
      </Consignor>
      <Freight>
        <paymentMethod>
          <Code.Content>token</Code.Content>
        </paymentMethod>
      </Freight>
      <GoodsMeasure>
        <sequence>
          <Numeric.Content>1000.00</Numeric.Content>
        </sequence>
        <grossMass>
          <Measure.Content>1000.00</Measure.Content>
        </grossMass>
      </GoodsMeasure>
      <PreviousDocument>
        <sequence>
          <Numeric.Content>1000.00</Numeric.Content>
        </sequence>
        <identification_2>
          <Identifier.Content>string</Identifier.Content>
        </identification_2>
        <type_3>
          <Code.Content>token</Code.Content>
        </type_3>
      </PreviousDocument>
      <SupportingDocument>
        <sequence>
          <Numeric.Content>1000.00</Numeric.Content>
        </sequence>
        <identification_2>
          <Identifier.Content>string</Identifier.Content>
        </identification_2>
        <type_3>
          <Code.Content>token</Code.Content>
        </type_3>
      </SupportingDocument>
      <UCR>
        <sequence>
          <Numeric.Content>1000.00</Numeric.Content>
        </sequence>
        <traderAssignedReference>
          <Identifier.Content>string</Identifier.Content>
        </traderAssignedReference>
      </UCR>
    </ConsignmentItem>
    <Consignor>
      <name>
        <Text.Content>string</Text.Content>
      </name>
      <identification_2>
        <Identifier.Content>string</Identifier.Content>
      </identification_2>
      <Address>
        <sequence>
          <Numeric.Content>1000.00</Numeric.Content>
        </sequence>
        <cityName>
          <Text.Content>string</Text.Content>
        </cityName>
        <country>
          <Code.Content>token</Code.Content>
        </country>
        <line>
          <Text.Content>string</Text.Content>
        </line>
        <postcode>
          <Identifier.Content>string</Identifier.Content>
        </postcode>
      </Address>
      <!--Optional:-->
      <sequence>
        <Numeric.Content>1000.00</Numeric.Content>
      </sequence>
    </Consignor>
    <Freight>
      <paymentMethod>
        <Code.Content>token</Code.Content>
      </paymentMethod>
    </Freight>
    <GoodsLocation>
      <name>
        <Text.Content>string</Text.Content>
      </name>
      <identification_2>
        <Identifier.Content>string</Identifier.Content>
      </identification_2>
      <type_2>
        <Code.Content>token</Code.Content>
      </type_2>
      <latitude>
        <Measure.Content>1000.00</Measure.Content>
      </latitude>
      <longitude>
        <Measure.Content>1000.00</Measure.Content>
      </longitude>
      <Address>
        <sequence>
          <Numeric.Content>1000.00</Numeric.Content>
        </sequence>
        <cityName>
          <Text.Content>string</Text.Content>
        </cityName>
        <country>
          <Code.Content>token</Code.Content>
        </country>
        <line>
          <Text.Content>string</Text.Content>
        </line>
        <postcode>
          <Identifier.Content>string</Identifier.Content>
        </postcode>
        <streetNumber>
          <Text.Content>string</Text.Content>
        </streetNumber>
      </Address>
      <sequence>
        <Numeric.Content>1000.00</Numeric.Content>
      </sequence>
      <identificationType_2>
        <Code.Content>token</Code.Content>
      </identificationType_2>
      <authorisationReferenceNumber>
        <Text.Content>string</Text.Content>
      </authorisationReferenceNumber>
      <CustomsOffice>
        <identification>
          <Identifier.Content>string</Identifier.Content>
        </identification>
      </CustomsOffice>
      <EconomicOperator>
        <identification_2>
          <Identifier.Content>string</Identifier.Content>
        </identification_2>
      </EconomicOperator>
      <Contact>
        <sequence>
          <Numeric.Content>1000.00</Numeric.Content>
        </sequence>
        <name>
          <Text.Content>string</Text.Content>
        </name>
        <Communication>
          <sequence>
            <Numeric.Content>1000.00</Numeric.Content>
          </sequence>
          <identification_2>
            <Identifier.Content>string</Identifier.Content>
          </identification_2>
          <type_8>
            <Code.Content>token</Code.Content>
          </type_8>
        </Communication>
      </Contact>
    </GoodsLocation>
    <Itinerary>
      <!--Optional:-->
      <sequence>
        <Numeric.Content>1000.00</Numeric.Content>
      </sequence>
      <routingCountry>
        <Code.Content>token</Code.Content>
      </routingCountry>
    </Itinerary>
    <PreviousDocument>
      <sequence>
        <Numeric.Content>1000.00</Numeric.Content>
      </sequence>
      <identification_2>
        <Identifier.Content>string</Identifier.Content>
      </identification_2>
      <type_3>
        <Code.Content>token</Code.Content>
      </type_3>
    </PreviousDocument>
    <SupportingDocument>
      <sequence>
        <Numeric.Content>1000.00</Numeric.Content>
      </sequence>
      <identification_2>
        <Identifier.Content>string</Identifier.Content>
      </identification_2>
      <type_3>
        <Code.Content>token</Code.Content>
      </type_3>
    </SupportingDocument>
    <TransportContractDocument>
      <sequence>
        <Numeric.Content>1000.00</Numeric.Content>
      </sequence>
      <identification_2>
        <Identifier.Content>string</Identifier.Content>
      </identification_2>
      <type_3>
        <Code.Content>token</Code.Content>
      </type_3>
    </TransportContractDocument>
    <TransportEquipment>
      <sequence>
        <Numeric.Content>1000.00</Numeric.Content>
      </sequence>
      <identification_2>
        <Identifier.Content>string</Identifier.Content>
      </identification_2>
      <sealsAffixed>
        <Quantity.Content>1000.00</Quantity.Content>
      </sealsAffixed>
      <Seal>
        <!--Optional:-->
        <sequence>
          <Numeric.Content>1000.00</Numeric.Content>
        </sequence>
        <identification_2>
          <Identifier.Content>string</Identifier.Content>
        </identification_2>
      </Seal>
    </TransportEquipment>
    <UCR>
      <sequence>
        <Numeric.Content>1000.00</Numeric.Content>
      </sequence>
      <traderAssignedReference>
        <Identifier.Content>string</Identifier.Content>
      </traderAssignedReference>
    </UCR>
  </Consignment>
</Declaration>